<annotation>
	<folder>42</folder>
	<filename>42_6001ab14aa6ea1428cb3c67b64ba5711.png</filename>
	<path>/home/alon/sda1/tsa-kaggle/data/raw/stage1/png_by_threat/42/42_6001ab14aa6ea1428cb3c67b64ba5711.png</path>
	<source>
		<database>Unknown</database>
	</source>
	<size>
		<width>512</width>
		<height>660</height>
		<depth>1</depth>
	</size>
	<segmented>0</segmented>
	<object>
		<name>threat</name>
		<pose>Unspecified</pose>
		<truncated>0</truncated>
		<difficult>0</difficult>
		<bndbox>
			<xmin>228</xmin>
			<ymin>279</ymin>
			<xmax>259</xmax>
			<ymax>332</ymax>
		</bndbox>
	</object>
</annotation>
