<annotation verified="yes">
	<folder>9</folder>
	<filename>9_8e1a7e8d24934e36e160985f32a8916b.png</filename>
	<path>/Users/alondaks/Desktop/png_aps_7/9/9_8e1a7e8d24934e36e160985f32a8916b.png</path>
	<source>
		<database>Unknown</database>
	</source>
	<size>
		<width>512</width>
		<height>660</height>
		<depth>1</depth>
	</size>
	<segmented>0</segmented>
	<object>
		<name>threat</name>
		<pose>Unspecified</pose>
		<truncated>0</truncated>
		<difficult>0</difficult>
		<bndbox>
			<xmin>192</xmin>
			<ymin>269</ymin>
			<xmax>243</xmax>
			<ymax>327</ymax>
		</bndbox>
	</object>
</annotation>
