<annotation>
	<folder>2</folder>
	<filename>2_9fbb8962adbe0cdcdea4bed068ab2d18.png</filename>
	<path>/Volumes/CRUZER/png_14_16/2/2_9fbb8962adbe0cdcdea4bed068ab2d18.png</path>
	<source>
		<database>Unknown</database>
	</source>
	<size>
		<width>512</width>
		<height>660</height>
		<depth>1</depth>
	</size>
	<segmented>0</segmented>
	<object>
		<name>threat</name>
		<pose>Unspecified</pose>
		<truncated>0</truncated>
		<difficult>0</difficult>
		<bndbox>
			<xmin>300</xmin>
			<ymin>518</ymin>
			<xmax>374</xmax>
			<ymax>568</ymax>
		</bndbox>
	</object>
</annotation>
