<annotation>
	<folder>46</folder>
	<filename>46_ca288818702681705703b3f23db7adc1.png</filename>
	<path>/home/alon/sda1/tsa-kaggle/data/raw/stage1/png_11/46/46_ca288818702681705703b3f23db7adc1.png</path>
	<source>
		<database>Unknown</database>
	</source>
	<size>
		<width>512</width>
		<height>660</height>
		<depth>1</depth>
	</size>
	<segmented>0</segmented>
	<object>
		<name>threat</name>
		<pose>Unspecified</pose>
		<truncated>0</truncated>
		<difficult>0</difficult>
		<bndbox>
			<xmin>175</xmin>
			<ymin>446</ymin>
			<xmax>228</xmax>
			<ymax>513</ymax>
		</bndbox>
	</object>
</annotation>
