<annotation>
	<folder>60</folder>
	<filename>60_9e0361fb3db6c25a0fb2e2059cdf9b19.png</filename>
	<path>/home/alon/sda1/tsa-kaggle/data/raw/stage1/png_11/60/60_9e0361fb3db6c25a0fb2e2059cdf9b19.png</path>
	<source>
		<database>Unknown</database>
	</source>
	<size>
		<width>512</width>
		<height>660</height>
		<depth>1</depth>
	</size>
	<segmented>0</segmented>
	<object>
		<name>threat</name>
		<pose>Unspecified</pose>
		<truncated>0</truncated>
		<difficult>0</difficult>
		<bndbox>
			<xmin>136</xmin>
			<ymin>489</ymin>
			<xmax>180</xmax>
			<ymax>537</ymax>
		</bndbox>
	</object>
</annotation>
