<annotation verified="yes">
	<folder>5</folder>
	<filename>5_f5283ffe7e484ffc640ebcf62b534f7b.png</filename>
	<path>/home/alon/sda1/tsa-kaggle/data/raw/stage1/png_14_aps/5/5_f5283ffe7e484ffc640ebcf62b534f7b.png</path>
	<source>
		<database>Unknown</database>
	</source>
	<size>
		<width>512</width>
		<height>660</height>
		<depth>1</depth>
	</size>
	<segmented>0</segmented>
	<object>
		<name>threat</name>
		<pose>Unspecified</pose>
		<truncated>0</truncated>
		<difficult>0</difficult>
		<bndbox>
			<xmin>279</xmin>
			<ymin>514</ymin>
			<xmax>324</xmax>
			<ymax>587</ymax>
		</bndbox>
	</object>
</annotation>
