<annotation verified="yes">
	<folder>12</folder>
	<filename>12_4d145eed143a972c0a19c9c4ec88524f.png</filename>
	<path>/home/alon/sda1/tsa-kaggle/data/raw/stage1/png_15_aps/12/12_4d145eed143a972c0a19c9c4ec88524f.png</path>
	<source>
		<database>Unknown</database>
	</source>
	<size>
		<width>512</width>
		<height>660</height>
		<depth>1</depth>
	</size>
	<segmented>0</segmented>
	<object>
		<name>threat</name>
		<pose>Unspecified</pose>
		<truncated>0</truncated>
		<difficult>0</difficult>
		<bndbox>
			<xmin>132</xmin>
			<ymin>584</ymin>
			<xmax>187</xmax>
			<ymax>648</ymax>
		</bndbox>
	</object>
</annotation>
