<annotation verified="yes">
	<folder>1</folder>
	<filename>1_e9e2bc4f4f319943935551d502fc11c2.png</filename>
	<path>/home/alon/sda1/tsa-kaggle/data/raw/stage1/png_15_aps/1/1_e9e2bc4f4f319943935551d502fc11c2.png</path>
	<source>
		<database>Unknown</database>
	</source>
	<size>
		<width>512</width>
		<height>660</height>
		<depth>1</depth>
	</size>
	<segmented>0</segmented>
	<object>
		<name>threat</name>
		<pose>Unspecified</pose>
		<truncated>0</truncated>
		<difficult>0</difficult>
		<bndbox>
			<xmin>165</xmin>
			<ymin>587</ymin>
			<xmax>196</xmax>
			<ymax>635</ymax>
		</bndbox>
	</object>
</annotation>
