<annotation verified="yes">
	<folder>50</folder>
	<filename>50_3e5e4ede1b6a4ec767480b261336b1b5.png</filename>
	<path>/home/alon/sda1/tsa-kaggle/data/raw/stage1/png_by_threat/50/50_3e5e4ede1b6a4ec767480b261336b1b5.png</path>
	<source>
		<database>Unknown</database>
	</source>
	<size>
		<width>512</width>
		<height>660</height>
		<depth>1</depth>
	</size>
	<segmented>0</segmented>
	<object>
		<name>threat</name>
		<pose>Unspecified</pose>
		<truncated>0</truncated>
		<difficult>0</difficult>
		<bndbox>
			<xmin>288</xmin>
			<ymin>296</ymin>
			<xmax>317</xmax>
			<ymax>341</ymax>
		</bndbox>
	</object>
</annotation>
