<annotation verified="yes">
	<folder>7</folder>
	<filename>7_d27f9e1fa0c2ca9ddae647815666f240.png</filename>
	<path>/home/alon/sda1/tsa-kaggle/data/raw/stage1/png_aps_2/7/7_d27f9e1fa0c2ca9ddae647815666f240.png</path>
	<source>
		<database>Unknown</database>
	</source>
	<size>
		<width>512</width>
		<height>660</height>
		<depth>1</depth>
	</size>
	<segmented>0</segmented>
	<object>
		<name>threat</name>
		<pose>Unspecified</pose>
		<truncated>0</truncated>
		<difficult>0</difficult>
		<bndbox>
			<xmin>355</xmin>
			<ymin>146</ymin>
			<xmax>402</xmax>
			<ymax>185</ymax>
		</bndbox>
	</object>
</annotation>
