<annotation>
	<folder>14</folder>
	<filename>14_3b46b70b40bb4f77a9da529f06356b50.png</filename>
	<path>/home/alon/sda1/tsa-kaggle/data/raw/stage1/png_aps_4/14/14_3b46b70b40bb4f77a9da529f06356b50.png</path>
	<source>
		<database>Unknown</database>
	</source>
	<size>
		<width>512</width>
		<height>660</height>
		<depth>1</depth>
	</size>
	<segmented>0</segmented>
	<object>
		<name>threat</name>
		<pose>Unspecified</pose>
		<truncated>0</truncated>
		<difficult>0</difficult>
		<bndbox>
			<xmin>315</xmin>
			<ymin>105</ymin>
			<xmax>367</xmax>
			<ymax>152</ymax>
		</bndbox>
	</object>
</annotation>
