<annotation>
	<folder>26</folder>
	<filename>26_1beb3744a2da2da340ef7b7f2b793e32.png</filename>
	<path>/home/alon/sda1/tsa-kaggle/data/raw/stage1/png_15/26/26_1beb3744a2da2da340ef7b7f2b793e32.png</path>
	<source>
		<database>Unknown</database>
	</source>
	<size>
		<width>512</width>
		<height>660</height>
		<depth>1</depth>
	</size>
	<segmented>0</segmented>
	<object>
		<name>threat</name>
		<pose>Unspecified</pose>
		<truncated>0</truncated>
		<difficult>0</difficult>
		<bndbox>
			<xmin>336</xmin>
			<ymin>588</ymin>
			<xmax>383</xmax>
			<ymax>648</ymax>
		</bndbox>
	</object>
</annotation>
