<annotation verified="yes">
	<folder>10</folder>
	<filename>10_cd37400d816ef77983bd89b9498295c6.png</filename>
	<path>/Users/gwynnedaks/Desktop/png_10_12/10/10_cd37400d816ef77983bd89b9498295c6.png</path>
	<source>
		<database>Unknown</database>
	</source>
	<size>
		<width>512</width>
		<height>660</height>
		<depth>1</depth>
	</size>
	<segmented>0</segmented>
	<object>
		<name>threat</name>
		<pose>Unspecified</pose>
		<truncated>0</truncated>
		<difficult>0</difficult>
		<bndbox>
			<xmin>251</xmin>
			<ymin>474</ymin>
			<xmax>339</xmax>
			<ymax>544</ymax>
		</bndbox>
	</object>
</annotation>
