<annotation>
	<folder>12</folder>
	<filename>12_57bb5dc4473179febe969679b2dd6976.png</filename>
	<path>/Users/gwynnedaks/Desktop/png_10_12/12/12_57bb5dc4473179febe969679b2dd6976.png</path>
	<source>
		<database>Unknown</database>
	</source>
	<size>
		<width>512</width>
		<height>660</height>
		<depth>1</depth>
	</size>
	<segmented>0</segmented>
	<object>
		<name>threat</name>
		<pose>Unspecified</pose>
		<truncated>0</truncated>
		<difficult>0</difficult>
		<bndbox>
			<xmin>222</xmin>
			<ymin>449</ymin>
			<xmax>319</xmax>
			<ymax>521</ymax>
		</bndbox>
	</object>
</annotation>
