<annotation>
	<folder>12</folder>
	<filename>12_71a28dc56c2039c74eba50a79831bfee.png</filename>
	<path>/Users/gwynnedaks/Desktop/png_10_12/12/12_71a28dc56c2039c74eba50a79831bfee.png</path>
	<source>
		<database>Unknown</database>
	</source>
	<size>
		<width>512</width>
		<height>660</height>
		<depth>1</depth>
	</size>
	<segmented>0</segmented>
	<object>
		<name>threat</name>
		<pose>Unspecified</pose>
		<truncated>0</truncated>
		<difficult>0</difficult>
		<bndbox>
			<xmin>307</xmin>
			<ymin>455</ymin>
			<xmax>364</xmax>
			<ymax>522</ymax>
		</bndbox>
	</object>
</annotation>
