<annotation>
	<folder>12</folder>
	<filename>12_a865f755f6e81d1b69c88343548f16fc.png</filename>
	<path>/Users/gwynnedaks/Desktop/png_10_12/12/12_a865f755f6e81d1b69c88343548f16fc.png</path>
	<source>
		<database>Unknown</database>
	</source>
	<size>
		<width>512</width>
		<height>660</height>
		<depth>1</depth>
	</size>
	<segmented>0</segmented>
	<object>
		<name>threat</name>
		<pose>Unspecified</pose>
		<truncated>0</truncated>
		<difficult>0</difficult>
		<bndbox>
			<xmin>247</xmin>
			<ymin>356</ymin>
			<xmax>313</xmax>
			<ymax>407</ymax>
		</bndbox>
	</object>
</annotation>
