<annotation verified="yes">
	<folder>26</folder>
	<filename>26_5cb8d7ef7176edcd0dd38e4c9921f185.png</filename>
	<path>/Volumes/CRUZER/png_10_12/26/26_5cb8d7ef7176edcd0dd38e4c9921f185.png</path>
	<source>
		<database>Unknown</database>
	</source>
	<size>
		<width>512</width>
		<height>660</height>
		<depth>1</depth>
	</size>
	<segmented>0</segmented>
	<object>
		<name>threat</name>
		<pose>Unspecified</pose>
		<truncated>0</truncated>
		<difficult>0</difficult>
		<bndbox>
			<xmin>164</xmin>
			<ymin>467</ymin>
			<xmax>218</xmax>
			<ymax>521</ymax>
		</bndbox>
	</object>
</annotation>
