<annotation verified="yes">
	<folder>26</folder>
	<filename>26_6574d7241cad5f378da7dce9dfec4cd0.png</filename>
	<path>/Volumes/CRUZER/png_10_12/26/26_6574d7241cad5f378da7dce9dfec4cd0.png</path>
	<source>
		<database>Unknown</database>
	</source>
	<size>
		<width>512</width>
		<height>660</height>
		<depth>1</depth>
	</size>
	<segmented>0</segmented>
	<object>
		<name>threat</name>
		<pose>Unspecified</pose>
		<truncated>0</truncated>
		<difficult>0</difficult>
		<bndbox>
			<xmin>173</xmin>
			<ymin>470</ymin>
			<xmax>213</xmax>
			<ymax>526</ymax>
		</bndbox>
	</object>
</annotation>
