<annotation verified="yes">
	<folder>7</folder>
	<filename>7_3f1c3df84fcc2a555d1a060ae1d24ed7.png</filename>
	<path>/home/alon/sda1/tsa-kaggle/data/raw/stage1/png_aps_17/7/7_3f1c3df84fcc2a555d1a060ae1d24ed7.png</path>
	<source>
		<database>Unknown</database>
	</source>
	<size>
		<width>512</width>
		<height>660</height>
		<depth>1</depth>
	</size>
	<segmented>0</segmented>
	<object>
		<name>threat</name>
		<pose>Unspecified</pose>
		<truncated>0</truncated>
		<difficult>0</difficult>
		<bndbox>
			<xmin>275</xmin>
			<ymin>242</ymin>
			<xmax>346</xmax>
			<ymax>287</ymax>
		</bndbox>
	</object>
</annotation>
