<annotation>
	<folder>42</folder>
	<filename>42_165b5c62911ad3158f2d2aed74f4a004.png</filename>
	<path>/home/alon/sda1/tsa-kaggle/data/raw/stage1/png_8/42/42_165b5c62911ad3158f2d2aed74f4a004.png</path>
	<source>
		<database>Unknown</database>
	</source>
	<size>
		<width>512</width>
		<height>660</height>
		<depth>1</depth>
	</size>
	<segmented>0</segmented>
	<object>
		<name>threat</name>
		<pose>Unspecified</pose>
		<truncated>0</truncated>
		<difficult>0</difficult>
		<bndbox>
			<xmin>234</xmin>
			<ymin>376</ymin>
			<xmax>291</xmax>
			<ymax>422</ymax>
		</bndbox>
	</object>
</annotation>
