<annotation verified="yes">
	<folder>4</folder>
	<filename>4_96dce5ceb9bcd90da1b17946b50eda75.png</filename>
	<path>/home/alon/sda1/tsa-kaggle/data/raw/stage1/png_aps_5/4/4_96dce5ceb9bcd90da1b17946b50eda75.png</path>
	<source>
		<database>Unknown</database>
	</source>
	<size>
		<width>512</width>
		<height>660</height>
		<depth>1</depth>
	</size>
	<segmented>0</segmented>
	<object>
		<name>threat</name>
		<pose>Unspecified</pose>
		<truncated>0</truncated>
		<difficult>0</difficult>
		<bndbox>
			<xmin>227</xmin>
			<ymin>230</ymin>
			<xmax>299</xmax>
			<ymax>273</ymax>
		</bndbox>
	</object>
</annotation>
